markdown_graphviz_svg.py
markdown_graphviz_svg-1.2.dist-info/LICENSE
markdown_graphviz_svg-1.2.dist-info/METADATA
markdown_graphviz_svg-1.2.dist-info/WHEEL
markdown_graphviz_svg-1.2.dist-info/top_level.txt
markdown_graphviz_svg-1.2.dist-info/RECORD
